[{"name":"sql.active_record","payload":{"sql":"SELECT  \"users\".* FROM \"users\"  WHERE \"users\".\"username\" = 'lwilsonsmith' LIMIT 1","name":"User Load","connection_id":70250808877300,"binds":[]},"time":"2013-10-25T09:28:41-04:00","transaction_id":"93fd39093b60607a111a","end":"2013-10-25T09:28:41-04:00","duration":0.502},{"name":"process_action.action_controller","payload":{"controller":"SessionsController","action":"create","params":{"utf8":"\u2713","authenticity_token":"jz0TCCSQfXTzB6oPKcbyHk29iWp4wLZMLnou7B3bG6g=","username":"lwilsonsmith","password":"[FILTERED]","button":"","action":"create","controller":"sessions"},"format":"html","method":"POST","path":"/sessions","status":302,"view_runtime":null,"db_runtime":0.502},"time":"2013-10-25T09:28:41-04:00","transaction_id":"68ceb9d4a3a4fcab055f","end":"2013-10-25T09:28:41-04:00","duration":82.18499999999999}]